[
    {
        "key": "dbln",
        "value": "%7B%22100062659540418%22%3A%224uFrb1G0%22%7D",
        "domain": "facebook.com",
        "path": "/login/device-based/",
        "hostOnly": false,
        "creation": "2025-08-04T18:07:28.554Z",
        "lastAccessed": "2025-08-04T18:07:28.554Z"
    },
    {
        "key": "datr",
        "value": "2O-NaBf_nkoE__OMJoBANchB",
        "domain": "facebook.com",
        "path": "/",
        "hostOnly": false,
        "creation": "2025-08-04T18:07:28.554Z",
        "lastAccessed": "2025-08-04T18:07:28.554Z"
    },
    {
        "key": "sb",
        "value": "2O-NaKoPQhXEkUoljgRFT7Ko",
        "domain": "facebook.com",
        "path": "/",
        "hostOnly": false,
        "creation": "2025-08-04T18:07:28.554Z",
        "lastAccessed": "2025-08-04T18:07:28.554Z"
    },
    {
        "key": "locale",
        "value": "en_GB",
        "domain": "facebook.com",
        "path": "/",
        "hostOnly": false,
        "creation": "2025-08-04T18:07:28.554Z",
        "lastAccessed": "2025-08-04T18:07:28.554Z"
    },
    {
        "key": "vpd",
        "value": "v1%3B823x424x2.549999952316284",
        "domain": "facebook.com",
        "path": "/",
        "hostOnly": false,
        "creation": "2025-08-04T18:07:28.554Z",
        "lastAccessed": "2025-08-04T18:07:28.554Z"
    },
    {
        "key": "dpr",
        "value": "2.549999952316284",
        "domain": "facebook.com",
        "path": "/",
        "hostOnly": false,
        "creation": "2025-08-04T18:07:28.554Z",
        "lastAccessed": "2025-08-04T18:07:28.554Z"
    },
    {
        "key": "ps_l",
        "value": "1",
        "domain": "facebook.com",
        "path": "/",
        "hostOnly": false,
        "creation": "2025-08-04T18:07:28.554Z",
        "lastAccessed": "2025-08-04T18:07:28.554Z"
    },
    {
        "key": "ps_n",
        "value": "1",
        "domain": "facebook.com",
        "path": "/",
        "hostOnly": false,
        "creation": "2025-08-04T18:07:28.554Z",
        "lastAccessed": "2025-08-04T18:07:28.554Z"
    },
    {
        "key": "pas",
        "value": "100062659540418%3AsVoBwkWFzE%2C100000783305388%3Ax142453RRL",
        "domain": "facebook.com",
        "path": "/",
        "hostOnly": false,
        "creation": "2025-08-04T18:07:28.554Z",
        "lastAccessed": "2025-08-04T18:07:28.554Z"
    },
    {
        "key": "m_pixel_ratio",
        "value": "2.549999952316284",
        "domain": "facebook.com",
        "path": "/",
        "hostOnly": false,
        "creation": "2025-08-04T18:07:28.555Z",
        "lastAccessed": "2025-08-04T18:07:28.555Z"
    },
    {
        "key": "wd",
        "value": "424x942",
        "domain": "facebook.com",
        "path": "/",
        "hostOnly": false,
        "creation": "2025-08-04T18:07:28.555Z",
        "lastAccessed": "2025-08-04T18:07:28.555Z"
    },
    {
        "key": "x-referer",
        "value": "eyJyIjoiL2hvbWUucGhwIiwiaCI6Ii8iLCJzIjoibSJ9",
        "domain": "facebook.com",
        "path": "/",
        "hostOnly": false,
        "creation": "2025-08-04T18:07:28.555Z",
        "lastAccessed": "2025-08-04T18:07:28.555Z"
    },
    {
        "key": "c_user",
        "value": "100062659540418",
        "domain": "facebook.com",
        "path": "/",
        "hostOnly": false,
        "creation": "2025-08-04T18:07:28.555Z",
        "lastAccessed": "2025-08-04T18:07:28.555Z"
    },
    {
        "key": "xs",
        "value": "8%3AkBpMcIQru2GtrQ%3A2%3A1754330838%3A-1%3A-1",
        "domain": "facebook.com",
        "path": "/",
        "hostOnly": false,
        "creation": "2025-08-04T18:07:28.555Z",
        "lastAccessed": "2025-08-04T18:07:28.555Z"
    },
    {
        "key": "fr",
        "value": "1hPr3zDPH2lFZPpCr.AWfuPBevGMubz1XTm_HJybbr6qLr_M6DL1zUuuV-d2wCS7PZWmw.BokPa4..AAA.0.0.BokPbZ.AWeDBEzVxwr13Z7hwo2JjzyPzrA",
        "domain": "facebook.com",
        "path": "/",
        "hostOnly": false,
        "creation": "2025-08-04T18:07:28.555Z",
        "lastAccessed": "2025-08-04T18:07:28.555Z"
    },
    {
        "key": "fbl_st",
        "value": "101724227%3BT%3A29238847",
        "domain": "facebook.com",
        "path": "/",
        "hostOnly": false,
        "creation": "2025-08-04T18:07:28.555Z",
        "lastAccessed": "2025-08-04T18:07:28.555Z"
    },
    {
        "key": "wl_cbv",
        "value": "v2%3Bclient_version%3A2884%3Btimestamp%3A1754330841",
        "domain": "facebook.com",
        "path": "/",
        "hostOnly": false,
        "creation": "2025-08-04T18:07:28.555Z",
        "lastAccessed": "2025-08-04T18:07:28.555Z"
    }
]
